finam_regrid/__init__.py
finam_regrid/_version.py
finam_regrid/adapter.py
finam_regrid/tools.py
finam_regrid-0.1.0.dist-info/METADATA
finam_regrid-0.1.0.dist-info/WHEEL
finam_regrid-0.1.0.dist-info/licenses/AUTHORS.md
finam_regrid-0.1.0.dist-info/licenses/COPYING
finam_regrid-0.1.0.dist-info/licenses/COPYING.LESSER
finam_regrid-0.1.0.dist-info/licenses/LICENSE.md
finam_regrid-0.1.0.dist-info/RECORD
